streamlit_ext/__init__.py
streamlit_ext/container.py
streamlit_ext/paramed_element.py
streamlit_ext/st_ext.py
streamlit_ext-0.1.19.dist-info/licenses/LICENSE
streamlit_ext-0.1.19.dist-info/METADATA
streamlit_ext-0.1.19.dist-info/WHEEL
streamlit_ext-0.1.19.dist-info/top_level.txt
streamlit_ext-0.1.19.dist-info/RECORD
