Metadata-Version: 2.4
Name: streamlit-ext
Version: 0.1.19
Summary: Small handy widgets for streamlit, e.g. download button which won't cause rerun, set page width
Author-email: John Lyu <paleneutron@outlook.com>
License-Expression: MIT
Project-URL: Source Code, https://github.com/PaleNeutron/streamlit-ext
Keywords: streamlit,widgets
Requires-Python: >=3.8
License-File: LICENSE
Requires-Dist: streamlit>=1.39.0
Requires-Dist: packaging
Provides-Extra: dev
Requires-Dist: mypy; extra == "dev"
Requires-Dist: ruff>=0.12; extra == "dev"
Provides-Extra: test
Requires-Dist: pytest>=7.1; extra == "test"
Requires-Dist: pytest-cov>=3.0.0; extra == "test"
Requires-Dist: pandas; extra == "test"
Requires-Dist: openpyxl; extra == "test"
Dynamic: license-file
